MANIFEST.in
README.txt
setup.py
Pygmie.egg-info/PKG-INFO
Pygmie.egg-info/SOURCES.txt
Pygmie.egg-info/dependency_links.txt
Pygmie.egg-info/entry_points.txt
Pygmie.egg-info/not-zip-safe
Pygmie.egg-info/requires.txt
Pygmie.egg-info/top_level.txt
pygmie/__init__.py
pygmie/postgres.py
pygmie/pygmie.py
pygmie/static/ace/ace.js
pygmie/static/ace/ext-searchbox.js
pygmie/static/ace/ext-spellcheck.js
pygmie/static/ace/ext-static_highlight.js
pygmie/static/ace/ext-textarea.js
pygmie/static/ace/keybinding-emacs.js
pygmie/static/ace/keybinding-vim.js
pygmie/static/ace/mode-abap.js
pygmie/static/ace/mode-asciidoc.js
pygmie/static/ace/mode-c9search.js
pygmie/static/ace/mode-c_cpp.js
pygmie/static/ace/mode-clojure.js
pygmie/static/ace/mode-coffee.js
pygmie/static/ace/mode-coldfusion.js
pygmie/static/ace/mode-csharp.js
pygmie/static/ace/mode-css.js
pygmie/static/ace/mode-curly.js
pygmie/static/ace/mode-dart.js
pygmie/static/ace/mode-diff.js
pygmie/static/ace/mode-django.js
pygmie/static/ace/mode-dot.js
pygmie/static/ace/mode-glsl.js
pygmie/static/ace/mode-golang.js
pygmie/static/ace/mode-groovy.js
pygmie/static/ace/mode-haml.js
pygmie/static/ace/mode-haxe.js
pygmie/static/ace/mode-html.js
pygmie/static/ace/mode-jade.js
pygmie/static/ace/mode-java.js
pygmie/static/ace/mode-javascript.js
pygmie/static/ace/mode-json.js
pygmie/static/ace/mode-jsp.js
pygmie/static/ace/mode-jsx.js
pygmie/static/ace/mode-latex.js
pygmie/static/ace/mode-less.js
pygmie/static/ace/mode-liquid.js
pygmie/static/ace/mode-lisp.js
pygmie/static/ace/mode-livescript.js
pygmie/static/ace/mode-lua.js
pygmie/static/ace/mode-luapage.js
pygmie/static/ace/mode-lucene.js
pygmie/static/ace/mode-makefile.js
pygmie/static/ace/mode-markdown.js
pygmie/static/ace/mode-objectivec.js
pygmie/static/ace/mode-ocaml.js
pygmie/static/ace/mode-perl.js
pygmie/static/ace/mode-pgsql.js
pygmie/static/ace/mode-php.js
pygmie/static/ace/mode-powershell.js
pygmie/static/ace/mode-python.js
pygmie/static/ace/mode-r.js
pygmie/static/ace/mode-rdoc.js
pygmie/static/ace/mode-rhtml.js
pygmie/static/ace/mode-ruby.js
pygmie/static/ace/mode-scad.js
pygmie/static/ace/mode-scala.js
pygmie/static/ace/mode-scheme.js
pygmie/static/ace/mode-scss.js
