Metadata-Version: 1.0
Name: Pygmie
Version: 1.4
Summary: Webinterface for working with PostgreSQL queries
Home-page: https://bitbucket.org/sras/py-pg-query-maker
Author: Sandeep.C.R
Author-email: sandeepcr2@gmail.com
License: MIT
Platform: UNKNOWN
